{"isDone":false,"isDoneUserId":"265dd9ab-b5da-4abd-92b1-668575187b06","testState":"none","testUserId":"a9c18e03-d113-4e46-9e69-de5adff7047a","isGoldenRequired":true,"isBackLog":false,"filesIds":[],"id":"deca1dd6-6e86-4e6a-b692-0a9c2f3b2485","uniqueNumber":161,"name":"[{\"insert\":\"При успешной отправке файлов из каталога - отображать текст \\\"Success! Sent to Google Cloud\\\" и кнопку \\\"back to Catalog\\\". При нажатии - возвращает на экран \\\"Catalog\\\".\\n\"}]","priority":6,"type":"requirement","tagsIds":[],"history":[{"id":"6001f75d-92d9-48cf-bc11-ceb288b6f215","text":"Требование создано","userId":"4dfa7bd1-7748-440b-8678-a00a8af56d25","type":"create","comment":"","data":{},"date":"2025-02-10T11:52:17.643","filesIds":[]}],"creatorUserId":"4dfa7bd1-7748-440b-8678-a00a8af56d25"}