{"isDone":true,"isDoneUserId":"cee5d4b9-0296-476f-a350-e654c604dbaa","testState":"done","testUserId":"022d60e8-b73c-4f06-9226-395ed87c949d","isGoldenRequired":true,"isBackLog":false,"isInfoRequestUserId":"022d60e8-b73c-4f06-9226-395ed87c949d","filesIds":[],"id":"35868114-f6ca-429c-895d-7256162fe29b","uniqueNumber":33,"name":"[{\"insert\":\"При успешной отправке фалов - отображать текст \\\"Success! Sent to Google Cloud\\\" и кнопку \\\"Enter new VIN-code\\\". При нажатии - возвращает на пустой экран \\\"General\\\"\\n\"}]","priority":4,"type":"requirement","tagsIds":[],"history":[{"id":"290512b9-d1a1-4bbf-8f89-84eda8c592a4","text":"Требование изменено","userId":"022d60e8-b73c-4f06-9226-395ed87c949d","type":"change","comment":"","data":{"new":{"name":"[{\"insert\":\"При успешной отправке видео - отображать текст \\\"Success! Sent to Google Cloud\\\" и кнопку \\\"Enter new VIN-code\\\". При нажатии - возвращает на экран \\\"General\\\"\\n\"}]"},"old":{"name":"[{\"insert\":\"При успешной отправке видео - отображать текст \\\"Success! Sent to Amazon AWS\\\" и кнопку \\\"Enter new VIN-code\\\". При нажатии - возвращает на экран \\\"General\\\"\\n\"}]"}},"date":"2024-11-21T11:53:29.861","filesIds":[]},{"id":"e532e6e1-5310-427c-a012-99dc94ea4164","text":"Требование изменено","userId":"cee5d4b9-0296-476f-a350-e654c604dbaa","type":"change","comment":"Возвращает на заполеннный экран или пустой?","data":{"new":{"isDoneUserId":"cee5d4b9-0296-476f-a350-e654c604dbaa","isInfoRequest":true,"isInfoRequestUserId":"022d60e8-b73c-4f06-9226-395ed87c949d"},"old":{"isDoneUserId":"022d60e8-b73c-4f06-9226-395ed87c949d","isInfoRequest":false,"isInfoRequestUserId":""}},"date":"2024-12-04T13:27:05.600","filesIds":[]},{"id":"d9b2eb47-4cf9-4020-9d80-99f30edc6ba4","text":"Требование изменено","userId":"022d60e8-b73c-4f06-9226-395ed87c949d","type":"change","comment":"","data":{"new":{"name":"[{\"insert\":\"При успешной отправке видео - отображать текст \\\"Success! Sent to Google Cloud\\\" и кнопку \\\"Enter new VIN-code\\\". При нажатии - возвращает на пустой экран \\\"General\\\"\\n\"}]"},"old":{"name":"[{\"insert\":\"При успешной отправке видео - отображать текст \\\"Success! Sent to Google Cloud\\\" и кнопку \\\"Enter new VIN-code\\\". При нажатии - возвращает на экран \\\"General\\\"\\n\"}]"}},"date":"2024-12-04T11:29:50.094","filesIds":[]},{"id":"5bf04673-f347-465a-a81b-0c8acbd9f33e","text":"Требование изменено","userId":"022d60e8-b73c-4f06-9226-395ed87c949d","type":"change","comment":"","data":{"new":{"isInfoRequest":false},"old":{"isInfoRequest":true}},"date":"2024-12-04T11:29:54.484","filesIds":[]},{"id":"783b892b-99a2-495e-9393-9083a90e5301","text":"Требование изменено","userId":"cee5d4b9-0296-476f-a350-e654c604dbaa","type":"change","comment":"","data":{"new":{"isDone":true},"old":{"isDone":false}},"date":"2024-12-04T15:30:04.830","filesIds":[]},{"id":"4903d918-1ff0-424b-bc8a-7e7c7d1bc70c","text":"Требование изменено","userId":"cee5d4b9-0296-476f-a350-e654c604dbaa","type":"change","comment":"Почему написано про отправку видео, а не файлов?","data":{"new":{"isInfoRequest":true,"blocks":{}},"old":{"isInfoRequest":false,"blocks":{}}},"date":"2024-12-17T21:57:01.059","filesIds":[]},{"id":"6062aa3d-0ff1-4bcb-9ab1-83e639373bcb","text":"Требование изменено","userId":"022d60e8-b73c-4f06-9226-395ed87c949d","type":"change","comment":"Поправил","data":{"new":{"isInfoRequest":false,"blocks":{},"name":"[{\"insert\":\"При успешной отправке фалов - отображать текст \\\"Success! Sent to Google Cloud\\\" и кнопку \\\"Enter new VIN-code\\\". При нажатии - возвращает на пустой экран \\\"General\\\"\\n\"}]"},"old":{"isInfoRequest":true,"blocks":{},"name":"[{\"insert\":\"При успешной отправке видео - отображать текст \\\"Success! Sent to Google Cloud\\\" и кнопку \\\"Enter new VIN-code\\\". При нажатии - возвращает на пустой экран \\\"General\\\"\\n\"}]"}},"date":"2024-12-18T08:59:16.572","filesIds":[]},{"id":"19a4ae70-88b5-4e67-aa33-f2f3a33e970c","text":"Требование изменено","userId":"022d60e8-b73c-4f06-9226-395ed87c949d","type":"change","comment":"","data":{"new":{"testState":"done","blocks":{}},"old":{"testState":"none","blocks":{}}},"date":"2024-12-19T10:30:35.532","filesIds":[]}],"creatorUserId":""}